MANIFEST.in
README.md
setup.py
beanstalk/__init__.py
beanstalk/bs_ssh_entry
beanstalk/bsjack
beanstalk/decorators.py
beanstalk/validator.py
beanstalk/console/__init__.py
beanstalk/console/titles.py
beanstalk/default_settings/__init__.py
beanstalk/default_settings/app_settings.py
beanstalk/default_settings/server_settings.py
beanstalk/paths/__init__.py
beanstalk/paths/server.py
beanstalk/static/beanstalk_apache.conf
beanstalk/static/beanstalk_init.sh
beanstalk/static/beanstalk_sudoer
beanstalk/static/global_uwsgi.ini
beanstalk/static/uwsgi_build.ini
beanstalk/tasks/__init__.py
beanstalk/tasks/app.py
beanstalk/tasks/base_class.py
beanstalk/tasks/daemon.py
beanstalk/tasks/info.py
beanstalk/tasks/server.py
beanstalk/tasks/users.py
beanstalk/tasks/utils.py
beanstalk/tasks/action/__init__.py
beanstalk/tasks/action/django.py
beanstalk/tasks/action/server.py
beanstalk_stack.egg-info/PKG-INFO
beanstalk_stack.egg-info/SOURCES.txt
beanstalk_stack.egg-info/dependency_links.txt
beanstalk_stack.egg-info/not-zip-safe
beanstalk_stack.egg-info/requires.txt
beanstalk_stack.egg-info/top_level.txt