Metadata-Version: 1.1
Name: beanstalk-stack
Version: 0.1.90
Summary: Django base for common use
Home-page: https://bitbucket.org/sodastsai/beanstalk-stack/
Author: sodas tsai
Author-email: sodas@sodas.tw
License: Apache Software licence 2.0, see LICENCE.txt
Keywords: django
Platform: UNKNOWN
Classifier: Development Status :: 2 - Pre-Alpha
Classifier: License :: OSI Approved :: Apache Software License
Classifier: Intended Audience :: Developers
Classifier: Environment :: Web Environment
Classifier: Programming Language :: Python :: 2.6
Classifier: Programming Language :: Python :: 2.7
Classifier: Topic :: Internet
Classifier: Topic :: Software Development :: Libraries :: Python Modules
